odoo/addons/contract_price_revision/README.rst
odoo/addons/contract_price_revision/__init__.py
odoo/addons/contract_price_revision/__manifest__.py
odoo/addons/contract_price_revision/i18n/contract_price_revision.pot
odoo/addons/contract_price_revision/i18n/es.po
odoo/addons/contract_price_revision/models/__init__.py
odoo/addons/contract_price_revision/models/account_analytic_account.py
odoo/addons/contract_price_revision/models/account_analytic_invoice_line.py
odoo/addons/contract_price_revision/readme/CONTRIBUTORS.rst
odoo/addons/contract_price_revision/readme/DESCRIPTION.rst
odoo/addons/contract_price_revision/readme/USAGE.rst
odoo/addons/contract_price_revision/static/description/icon.png
odoo/addons/contract_price_revision/static/description/index.html
odoo/addons/contract_price_revision/tests/__init__.py
odoo/addons/contract_price_revision/tests/test_contract_price_revision.py
odoo/addons/contract_price_revision/views/account_analytic_account_views.xml
odoo/addons/contract_price_revision/wizards/__init__.py
odoo/addons/contract_price_revision/wizards/create_revision_line.py
odoo/addons/contract_price_revision/wizards/create_revision_line_views.xml
odoo11_addon_contract_price_revision-11.0.1.0.1.dist-info/METADATA
odoo11_addon_contract_price_revision-11.0.1.0.1.dist-info/WHEEL
odoo11_addon_contract_price_revision-11.0.1.0.1.dist-info/top_level.txt
odoo11_addon_contract_price_revision-11.0.1.0.1.dist-info/RECORD
